highlander/__init__.py
highlander/enums.py
highlander/type.py
highlander_enum-0.9.1.dist-info/METADATA
highlander_enum-0.9.1.dist-info/WHEEL
highlander_enum-0.9.1.dist-info/licenses/LICENSE
highlander_enum-0.9.1.dist-info/RECORD
