Metadata-Version: 2.4
Name: highlander-enum
Version: 0.9.1
Summary: Better enums including flags with subsets in which there can be only one... set.
Project-URL: Homepage, https://florean.github.io/highlander-enum/
Project-URL: Repository, https://github.com/florean/highlander-enum
Project-URL: Documentation, https://florean.github.io/highlander-enum/
Author-email: Nathan Florea <florean@gmail.com>
License-Expression: Apache-2.0
License-File: LICENSE
Keywords: enum,python
Classifier: Intended Audience :: Developers
Classifier: Programming Language :: Python
Classifier: Programming Language :: Python :: 3
Classifier: Programming Language :: Python :: 3.11
Classifier: Programming Language :: Python :: 3.12
Classifier: Programming Language :: Python :: 3.13
Classifier: Topic :: Software Development :: Libraries :: Python Modules
Requires-Python: <4.0,>=3.11
